{"meta": {"about_this_data": "\nCook County Jail Inmate data, scraped from\nhttp://www2.cookcountysheriff.org/search2/ nightly.\n\nLearn more about this API at\nhttps://github.com/sc3/cookcountyjail/wiki/API-guide\n\nLearn more about this project at\nhttps://github.com/sc3/cookcountyjail/\n\nThe data on jail inmates is not verified. Do not take the data as\ndefinitive, but rather as suggestive. This data can be used to develop\ninteresting questions, but it cannot be cited as factual.\n\nDeveloped by the Supreme Chi-Town Coding Crew\n(https://github.com/sc3/sc3)\n", "limit": 0, "offset": 0, "total_count": 103}, "objects": [{"booking_date": "2013-08-01", "female_as": 5, "female_b": 2, "female_bk": 843, "female_in": 3, "female_lb": 7, "female_lt": 35, "female_lw": 61, "female_w": 2, "female_wh": 213, "id": 136644, "male_as": 69, "male_b": 21, "male_bk": 9102, "male_in": 7, "male_lb": 33, "male_lt": 1219, "male_lw": 769, "male_w": 19, "male_wh": 1074, "resource_uri": "/api/1.0/dailypopulationcounts/136644/", "total": 13484}, {"booking_date": "2013-08-02", "female_as": 6, "female_b": 2, "female_bk": 842, "female_in": 3, "female_lb": 7, "female_lt": 35, "female_lw": 64, "female_w": 2, "female_wh": 217, "id": 136642, "male_as": 66, "male_b": 20, "male_bk": 9031, "male_in": 7, "male_lb": 32, "male_lt": 1215, "male_lw": 769, "male_w": 19, "male_wh": 1080, "resource_uri": "/api/1.0/dailypopulationcounts/136642/", "total": 13417}, {"booking_date": "2013-08-03", "female_as": 6, "female_b": 3, "female_bk": 829, "female_in": 3, "female_lb": 7, "female_lt": 36, "female_lw": 64, "female_w": 2, "female_wh": 215, "id": 136643, "male_as": 65, "male_b": 21, "male_bk": 9014, "male_in": 7, "male_lb": 32, "male_lt": 1214, "male_lw": 759, "male_w": 18, "male_wh": 1066, "resource_uri": "/api/1.0/dailypopulationcounts/136643/", "total": 13361}, {"booking_date": "2013-08-04", "female_as": 7, "female_b": 3, "female_bk": 848, "female_in": 3, "female_lb": 7, "female_lt": 35, "female_lw": 65, "female_w": 2, "female_wh": 219, "id": 136640, "male_as": 65, "male_b": 21, "male_bk": 9098, "male_in": 7, "male_lb": 32, "male_lt": 1221, "male_lw": 764, "male_w": 18, "male_wh": 1080, "resource_uri": "/api/1.0/dailypopulationcounts/136640/", "total": 13495}, {"booking_date": "2013-08-05", "female_as": 7, "female_b": 3, "female_bk": 863, "female_in": 3, "female_lb": 7, "female_lt": 34, "female_lw": 68, "female_w": 2, "female_wh": 226, "id": 136641, "male_as": 67, "male_b": 21, "male_bk": 9181, "male_in": 7, "male_lb": 33, "male_lt": 1226, "male_lw": 767, "male_w": 18, "male_wh": 1092, "resource_uri": "/api/1.0/dailypopulationcounts/136641/", "total": 13625}, {"booking_date": "2013-08-06", "female_as": 7, "female_b": 3, "female_bk": 871, "female_in": 3, "female_lb": 7, "female_lt": 36, "female_lw": 67, "female_w": 2, "female_wh": 231, "id": 136668, "male_as": 63, "male_b": 21, "male_bk": 9133, "male_in": 7, "male_lb": 32, "male_lt": 1221, "male_lw": 763, "male_w": 17, "male_wh": 1085, "resource_uri": "/api/1.0/dailypopulationcounts/136668/", "total": 13569}, {"booking_date": "2013-08-07", "female_as": 7, "female_b": 3, "female_bk": 856, "female_in": 2, "female_lb": 7, "female_lt": 36, "female_lw": 68, "female_w": 2, "female_wh": 224, "id": 136639, "male_as": 61, "male_b": 21, "male_bk": 9147, "male_in": 7, "male_lb": 33, "male_lt": 1212, "male_lw": 761, "male_w": 17, "male_wh": 1090, "resource_uri": "/api/1.0/dailypopulationcounts/136639/", "total": 13554}, {"booking_date": "2013-08-08", "female_as": 7, "female_b": 3, "female_bk": 848, "female_in": 2, "female_lb": 7, "female_lt": 36, "female_lw": 70, "female_w": 2, "female_wh": 217, "id": 136636, "male_as": 61, "male_b": 20, "male_bk": 9157, "male_in": 7, "male_lb": 33, "male_lt": 1215, "male_lw": 769, "male_w": 18, "male_wh": 1086, "resource_uri": "/api/1.0/dailypopulationcounts/136636/", "total": 13558}, {"booking_date": "2013-08-09", "female_as": 6, "female_b": 3, "female_bk": 857, "female_in": 1, "female_lb": 7, "female_lt": 36, "female_lw": 68, "female_w": 2, "female_wh": 210, "id": 136666, "male_as": 59, "male_b": 21, "male_bk": 9124, "male_in": 7, "male_lb": 33, "male_lt": 1207, "male_lw": 769, "male_w": 18, "male_wh": 1094, "resource_uri": "/api/1.0/dailypopulationcounts/136666/", "total": 13522}, {"booking_date": "2013-08-10", "female_as": 6, "female_b": 3, "female_bk": 858, "female_in": 0, "female_lb": 7, "female_lt": 37, "female_lw": 70, "female_w": 2, "female_wh": 207, "id": 136677, "male_as": 58, "male_b": 21, "male_bk": 9086, "male_in": 6, "male_lb": 33, "male_lt": 1205, "male_lw": 761, "male_w": 18, "male_wh": 1082, "resource_uri": "/api/1.0/dailypopulationcounts/136677/", "total": 13461}, {"booking_date": "2013-08-11", "female_as": 6, "female_b": 3, "female_bk": 864, "female_in": 0, "female_lb": 7, "female_lt": 37, "female_lw": 70, "female_w": 2, "female_wh": 213, "id": 136676, "male_as": 58, "male_b": 21, "male_bk": 9151, "male_in": 6, "male_lb": 34, "male_lt": 1215, "male_lw": 776, "male_w": 18, "male_wh": 1091, "resource_uri": "/api/1.0/dailypopulationcounts/136676/", "total": 13573}, {"booking_date": "2013-08-12", "female_as": 6, "female_b": 3, "female_bk": 883, "female_in": 0, "female_lb": 8, "female_lt": 36, "female_lw": 73, "female_w": 2, "female_wh": 214, "id": 136679, "male_as": 59, "male_b": 21, "male_bk": 9238, "male_in": 6, "male_lb": 34, "male_lt": 1228, "male_lw": 788, "male_w": 19, "male_wh": 1109, "resource_uri": "/api/1.0/dailypopulationcounts/136679/", "total": 13728}, {"booking_date": "2013-08-13", "female_as": 6, "female_b": 3, "female_bk": 892, "female_in": 0, "female_lb": 8, "female_lt": 36, "female_lw": 71, "female_w": 2, "female_wh": 210, "id": 136678, "male_as": 59, "male_b": 22, "male_bk": 9232, "male_in": 6, "male_lb": 34, "male_lt": 1226, "male_lw": 790, "male_w": 18, "male_wh": 1095, "resource_uri": "/api/1.0/dailypopulationcounts/136678/", "total": 13711}, {"booking_date": "2013-08-14", "female_as": 6, "female_b": 3, "female_bk": 898, "female_in": 0, "female_lb": 8, "female_lt": 36, "female_lw": 70, "female_w": 2, "female_wh": 207, "id": 136738, "male_as": 59, "male_b": 22, "male_bk": 9209, "male_in": 6, "male_lb": 33, "male_lt": 1220, "male_lw": 799, "male_w": 18, "male_wh": 1088, "resource_uri": "/api/1.0/dailypopulationcounts/136738/", "total": 13685}, {"booking_date": "2013-08-15", "female_as": 6, "female_b": 3, "female_bk": 884, "female_in": 0, "female_lb": 7, "female_lt": 35, "female_lw": 73, "female_w": 2, "female_wh": 200, "id": 136672, "male_as": 60, "male_b": 22, "male_bk": 9231, "male_in": 6, "male_lb": 34, "male_lt": 1223, "male_lw": 786, "male_w": 18, "male_wh": 1087, "resource_uri": "/api/1.0/dailypopulationcounts/136672/", "total": 13678}, {"booking_date": "2013-08-16", "female_as": 6, "female_b": 3, "female_bk": 887, "female_in": 0, "female_lb": 7, "female_lt": 34, "female_lw": 75, "female_w": 2, "female_wh": 202, "id": 136675, "male_as": 61, "male_b": 23, "male_bk": 9233, "male_in": 6, "male_lb": 34, "male_lt": 1212, "male_lw": 778, "male_w": 18, "male_wh": 1084, "resource_uri": "/api/1.0/dailypopulationcounts/136675/", "total": 13666}, {"booking_date": "2013-08-17", "female_as": 7, "female_b": 3, "female_bk": 891, "female_in": 0, "female_lb": 7, "female_lt": 34, "female_lw": 72, "female_w": 2, "female_wh": 195, "id": 136674, "male_as": 59, "male_b": 23, "male_bk": 9205, "male_in": 6, "male_lb": 35, "male_lt": 1216, "male_lw": 769, "male_w": 18, "male_wh": 1077, "resource_uri": "/api/1.0/dailypopulationcounts/136674/", "total": 13620}, {"booking_date": "2013-08-18", "female_as": 7, "female_b": 3, "female_bk": 903, "female_in": 0, "female_lb": 7, "female_lt": 35, "female_lw": 71, "female_w": 2, "female_wh": 197, "id": 136670, "male_as": 58, "male_b": 23, "male_bk": 9278, "male_in": 6, "male_lb": 38, "male_lt": 1234, "male_lw": 779, "male_w": 18, "male_wh": 1088, "resource_uri": "/api/1.0/dailypopulationcounts/136670/", "total": 13748}, {"booking_date": "2013-08-19", "female_as": 7, "female_b": 3, "female_bk": 912, "female_in": 0, "female_lb": 7, "female_lt": 35, "female_lw": 73, "female_w": 2, "female_wh": 205, "id": 136669, "male_as": 59, "male_b": 22, "male_bk": 9298, "male_in": 6, "male_lb": 38, "male_lt": 1244, "male_lw": 788, "male_w": 18, "male_wh": 1090, "resource_uri": "/api/1.0/dailypopulationcounts/136669/", "total": 13808}, {"booking_date": "2013-08-20", "female_as": 7, "female_b": 3, "female_bk": 914, "female_in": 0, "female_lb": 7, "female_lt": 34, "female_lw": 69, "female_w": 1, "female_wh": 208, "id": 136699, "male_as": 60, "male_b": 22, "male_bk": 9364, "male_in": 6, "male_lb": 39, "male_lt": 1254, "male_lw": 786, "male_w": 18, "male_wh": 1082, "resource_uri": "/api/1.0/dailypopulationcounts/136699/", "total": 13875}, {"booking_date": "2013-08-21", "female_as": 6, "female_b": 2, "female_bk": 901, "female_in": 0, "female_lb": 7, "female_lt": 34, "female_lw": 71, "female_w": 1, "female_wh": 204, "id": 136700, "male_as": 58, "male_b": 21, "male_bk": 9362, "male_in": 6, "male_lb": 38, "male_lt": 1244, "male_lw": 787, "male_w": 17, "male_wh": 1077, "resource_uri": "/api/1.0/dailypopulationcounts/136700/", "total": 13837}, {"booking_date": "2013-08-22", "female_as": 6, "female_b": 2, "female_bk": 880, "female_in": 0, "female_lb": 7, "female_lt": 34, "female_lw": 70, "female_w": 1, "female_wh": 207, "id": 136701, "male_as": 60, "male_b": 22, "male_bk": 9330, "male_in": 6, "male_lb": 37, "male_lt": 1244, "male_lw": 790, "male_w": 17, "male_wh": 1087, "resource_uri": "/api/1.0/dailypopulationcounts/136701/", "total": 13801}, {"booking_date": "2013-08-23", "female_as": 6, "female_b": 2, "female_bk": 898, "female_in": 0, "female_lb": 7, "female_lt": 34, "female_lw": 72, "female_w": 1, "female_wh": 211, "id": 136696, "male_as": 60, "male_b": 22, "male_bk": 9360, "male_in": 7, "male_lb": 37, "male_lt": 1233, "male_lw": 787, "male_w": 17, "male_wh": 1091, "resource_uri": "/api/1.0/dailypopulationcounts/136696/", "total": 13846}, {"booking_date": "2013-08-24", "female_as": 6, "female_b": 2, "female_bk": 891, "female_in": 0, "female_lb": 7, "female_lt": 37, "female_lw": 78, "female_w": 1, "female_wh": 209, "id": 136703, "male_as": 58, "male_b": 21, "male_bk": 9292, "male_in": 7, "male_lb": 36, "male_lt": 1229, "male_lw": 786, "male_w": 17, "male_wh": 1074, "resource_uri": "/api/1.0/dailypopulationcounts/136703/", "total": 13752}, {"booking_date": "2013-08-25", "female_as": 6, "female_b": 2, "female_bk": 899, "female_in": 0, "female_lb": 6, "female_lt": 37, "female_lw": 78, "female_w": 1, "female_wh": 208, "id": 136712, "male_as": 61, "male_b": 21, "male_bk": 9366, "male_in": 8, "male_lb": 37, "male_lt": 1259, "male_lw": 794, "male_w": 17, "male_wh": 1085, "resource_uri": "/api/1.0/dailypopulationcounts/136712/", "total": 13886}, {"booking_date": "2013-08-26", "female_as": 6, "female_b": 2, "female_bk": 905, "female_in": 0, "female_lb": 7, "female_lt": 36, "female_lw": 80, "female_w": 1, "female_wh": 210, "id": 136498, "male_as": 61, "male_b": 21, "male_bk": 9466, "male_in": 9, "male_lb": 36, "male_lt": 1281, "male_lw": 806, "male_w": 17, "male_wh": 1096, "resource_uri": "/api/1.0/dailypopulationcounts/136498/", "total": 14041}, {"booking_date": "2013-08-27", "female_as": 5, "female_b": 2, "female_bk": 905, "female_in": 0, "female_lb": 7, "female_lt": 36, "female_lw": 79, "female_w": 1, "female_wh": 213, "id": 136500, "male_as": 61, "male_b": 21, "male_bk": 9436, "male_in": 9, "male_lb": 36, "male_lt": 1264, "male_lw": 809, "male_w": 18, "male_wh": 1093, "resource_uri": "/api/1.0/dailypopulationcounts/136500/", "total": 13996}, {"booking_date": "2013-08-28", "female_as": 5, "female_b": 2, "female_bk": 907, "female_in": 0, "female_lb": 6, "female_lt": 36, "female_lw": 77, "female_w": 1, "female_wh": 211, "id": 136707, "male_as": 62, "male_b": 20, "male_bk": 9435, "male_in": 9, "male_lb": 37, "male_lt": 1257, "male_lw": 808, "male_w": 18, "male_wh": 1104, "resource_uri": "/api/1.0/dailypopulationcounts/136707/", "total": 13996}, {"booking_date": "2013-08-29", "female_as": 6, "female_b": 1, "female_bk": 891, "female_in": 0, "female_lb": 6, "female_lt": 36, "female_lw": 79, "female_w": 1, "female_wh": 207, "id": 136708, "male_as": 62, "male_b": 22, "male_bk": 9474, "male_in": 9, "male_lb": 37, "male_lt": 1263, "male_lw": 806, "male_w": 18, "male_wh": 1109, "resource_uri": "/api/1.0/dailypopulationcounts/136708/", "total": 14028}, {"booking_date": "2013-08-30", "female_as": 7, "female_b": 1, "female_bk": 902, "female_in": 0, "female_lb": 6, "female_lt": 37, "female_lw": 79, "female_w": 1, "female_wh": 205, "id": 136736, "male_as": 58, "male_b": 22, "male_bk": 9436, "male_in": 9, "male_lb": 38, "male_lt": 1261, "male_lw": 808, "male_w": 18, "male_wh": 1108, "resource_uri": "/api/1.0/dailypopulationcounts/136736/", "total": 13997}, {"booking_date": "2013-08-31", "female_as": 7, "female_b": 1, "female_bk": 900, "female_in": 0, "female_lb": 6, "female_lt": 35, "female_lw": 78, "female_w": 1, "female_wh": 209, "id": 136735, "male_as": 57, "male_b": 21, "male_bk": 9380, "male_in": 9, "male_lb": 37, "male_lt": 1250, "male_lw": 792, "male_w": 20, "male_wh": 1102, "resource_uri": "/api/1.0/dailypopulationcounts/136735/", "total": 13906}, {"booking_date": "2013-09-01", "female_as": 6, "female_b": 1, "female_bk": 901, "female_in": 0, "female_lb": 6, "female_lt": 35, "female_lw": 82, "female_w": 1, "female_wh": 214, "id": 136588, "male_as": 57, "male_b": 21, "male_bk": 9432, "male_in": 10, "male_lb": 38, "male_lt": 1252, "male_lw": 802, "male_w": 20, "male_wh": 1114, "resource_uri": "/api/1.0/dailypopulationcounts/136588/", "total": 13993}, {"booking_date": "2013-09-02", "female_as": 6, "female_b": 1, "female_bk": 914, "female_in": 0, "female_lb": 6, "female_lt": 35, "female_lw": 85, "female_w": 1, "female_wh": 216, "id": 136797, "male_as": 57, "male_b": 22, "male_bk": 9503, "male_in": 10, "male_lb": 37, "male_lt": 1270, "male_lw": 812, "male_w": 20, "male_wh": 1131, "resource_uri": "/api/1.0/dailypopulationcounts/136797/", "total": 14127}, {"booking_date": "2013-09-03", "female_as": 6, "female_b": 1, "female_bk": 918, "female_in": 0, "female_lb": 6, "female_lt": 35, "female_lw": 85, "female_w": 1, "female_wh": 221, "id": 136597, "male_as": 58, "male_b": 22, "male_bk": 9599, "male_in": 10, "male_lb": 38, "male_lt": 1275, "male_lw": 823, "male_w": 21, "male_wh": 1150, "resource_uri": "/api/1.0/dailypopulationcounts/136597/", "total": 14270}, {"booking_date": "2013-09-04", "female_as": 6, "female_b": 1, "female_bk": 913, "female_in": 1, "female_lb": 6, "female_lt": 36, "female_lw": 84, "female_w": 1, "female_wh": 222, "id": 136523, "male_as": 57, "male_b": 22, "male_bk": 9513, "male_in": 10, "male_lb": 37, "male_lt": 1259, "male_lw": 820, "male_w": 21, "male_wh": 1146, "resource_uri": "/api/1.0/dailypopulationcounts/136523/", "total": 14156}, {"booking_date": "2013-09-05", "female_as": 6, "female_b": 1, "female_bk": 894, "female_in": 1, "female_lb": 6, "female_lt": 37, "female_lw": 86, "female_w": 1, "female_wh": 225, "id": 136501, "male_as": 57, "male_b": 21, "male_bk": 9516, "male_in": 10, "male_lb": 37, "male_lt": 1261, "male_lw": 826, "male_w": 20, "male_wh": 1145, "resource_uri": "/api/1.0/dailypopulationcounts/136501/", "total": 14151}, {"booking_date": "2013-09-06", "female_as": 6, "female_b": 1, "female_bk": 903, "female_in": 1, "female_lb": 6, "female_lt": 39, "female_lw": 84, "female_w": 1, "female_wh": 225, "id": 136667, "male_as": 57, "male_b": 21, "male_bk": 9498, "male_in": 10, "male_lb": 37, "male_lt": 1259, "male_lw": 827, "male_w": 20, "male_wh": 1151, "resource_uri": "/api/1.0/dailypopulationcounts/136667/", "total": 14147}, {"booking_date": "2013-09-07", "female_as": 6, "female_b": 1, "female_bk": 897, "female_in": 0, "female_lb": 6, "female_lt": 38, "female_lw": 81, "female_w": 1, "female_wh": 222, "id": 136542, "male_as": 54, "male_b": 23, "male_bk": 9454, "male_in": 9, "male_lb": 37, "male_lt": 1257, "male_lw": 826, "male_w": 20, "male_wh": 1132, "resource_uri": "/api/1.0/dailypopulationcounts/136542/", "total": 14065}, {"booking_date": "2013-09-08", "female_as": 6, "female_b": 1, "female_bk": 909, "female_in": 0, "female_lb": 6, "female_lt": 39, "female_lw": 83, "female_w": 1, "female_wh": 223, "id": 136630, "male_as": 54, "male_b": 23, "male_bk": 9496, "male_in": 9, "male_lb": 37, "male_lt": 1266, "male_lw": 831, "male_w": 20, "male_wh": 1133, "resource_uri": "/api/1.0/dailypopulationcounts/136630/", "total": 14138}, {"booking_date": "2013-09-09", "female_as": 6, "female_b": 1, "female_bk": 917, "female_in": 0, "female_lb": 6, "female_lt": 40, "female_lw": 85, "female_w": 1, "female_wh": 227, "id": 136732, "male_as": 54, "male_b": 23, "male_bk": 9580, "male_in": 9, "male_lb": 37, "male_lt": 1283, "male_lw": 837, "male_w": 21, "male_wh": 1149, "resource_uri": "/api/1.0/dailypopulationcounts/136732/", "total": 14277}, {"booking_date": "2013-09-10", "female_as": 6, "female_b": 1, "female_bk": 913, "female_in": 0, "female_lb": 6, "female_lt": 39, "female_lw": 87, "female_w": 1, "female_wh": 224, "id": 136775, "male_as": 53, "male_b": 23, "male_bk": 9581, "male_in": 9, "male_lb": 38, "male_lt": 1270, "male_lw": 842, "male_w": 23, "male_wh": 1139, "resource_uri": "/api/1.0/dailypopulationcounts/136775/", "total": 14256}, {"booking_date": "2013-09-11", "female_as": 6, "female_b": 2, "female_bk": 917, "female_in": 0, "female_lb": 6, "female_lt": 40, "female_lw": 87, "female_w": 1, "female_wh": 225, "id": 136681, "male_as": 53, "male_b": 23, "male_bk": 9572, "male_in": 9, "male_lb": 36, "male_lt": 1259, "male_lw": 840, "male_w": 21, "male_wh": 1142, "resource_uri": "/api/1.0/dailypopulationcounts/136681/", "total": 14240}, {"booking_date": "2013-09-12", "female_as": 7, "female_b": 2, "female_bk": 897, "female_in": 0, "female_lb": 7, "female_lt": 37, "female_lw": 82, "female_w": 1, "female_wh": 213, "id": 136497, "male_as": 52, "male_b": 23, "male_bk": 9604, "male_in": 10, "male_lb": 36, "male_lt": 1264, "male_lw": 840, "male_w": 21, "male_wh": 1152, "resource_uri": "/api/1.0/dailypopulationcounts/136497/", "total": 14249}, {"booking_date": "2013-09-13", "female_as": 7, "female_b": 2, "female_bk": 904, "female_in": 0, "female_lb": 7, "female_lt": 37, "female_lw": 81, "female_w": 1, "female_wh": 218, "id": 136516, "male_as": 53, "male_b": 22, "male_bk": 9562, "male_in": 10, "male_lb": 37, "male_lt": 1264, "male_lw": 842, "male_w": 20, "male_wh": 1148, "resource_uri": "/api/1.0/dailypopulationcounts/136516/", "total": 14216}, {"booking_date": "2013-09-14", "female_as": 7, "female_b": 2, "female_bk": 894, "female_in": 0, "female_lb": 7, "female_lt": 37, "female_lw": 80, "female_w": 1, "female_wh": 219, "id": 136688, "male_as": 52, "male_b": 22, "male_bk": 9492, "male_in": 9, "male_lb": 37, "male_lt": 1255, "male_lw": 841, "male_w": 18, "male_wh": 1140, "resource_uri": "/api/1.0/dailypopulationcounts/136688/", "total": 14114}, {"booking_date": "2013-09-15", "female_as": 7, "female_b": 2, "female_bk": 903, "female_in": 0, "female_lb": 7, "female_lt": 37, "female_lw": 80, "female_w": 1, "female_wh": 221, "id": 136691, "male_as": 52, "male_b": 22, "male_bk": 9532, "male_in": 9, "male_lb": 39, "male_lt": 1262, "male_lw": 845, "male_w": 18, "male_wh": 1156, "resource_uri": "/api/1.0/dailypopulationcounts/136691/", "total": 14194}, {"booking_date": "2013-09-16", "female_as": 7, "female_b": 2, "female_bk": 909, "female_in": 0, "female_lb": 7, "female_lt": 37, "female_lw": 81, "female_w": 1, "female_wh": 221, "id": 136740, "male_as": 51, "male_b": 22, "male_bk": 9612, "male_in": 9, "male_lb": 39, "male_lt": 1285, "male_lw": 851, "male_w": 18, "male_wh": 1169, "resource_uri": "/api/1.0/dailypopulationcounts/136740/", "total": 14322}, {"booking_date": "2013-09-17", "female_as": 7, "female_b": 2, "female_bk": 902, "female_in": 0, "female_lb": 7, "female_lt": 37, "female_lw": 82, "female_w": 1, "female_wh": 221, "id": 136686, "male_as": 50, "male_b": 22, "male_bk": 9595, "male_in": 9, "male_lb": 37, "male_lt": 1268, "male_lw": 848, "male_w": 18, "male_wh": 1176, "resource_uri": "/api/1.0/dailypopulationcounts/136686/", "total": 14283}, {"booking_date": "2013-09-18", "female_as": 7, "female_b": 2, "female_bk": 901, "female_in": 0, "female_lb": 7, "female_lt": 37, "female_lw": 84, "female_w": 1, "female_wh": 225, "id": 136783, "male_as": 52, "male_b": 23, "male_bk": 9547, "male_in": 9, "male_lb": 37, "male_lt": 1260, "male_lw": 846, "male_w": 18, "male_wh": 1160, "resource_uri": "/api/1.0/dailypopulationcounts/136783/", "total": 14217}, {"booking_date": "2013-09-19", "female_as": 7, "female_b": 2, "female_bk": 906, "female_in": 0, "female_lb": 7, "female_lt": 36, "female_lw": 82, "female_w": 1, "female_wh": 215, "id": 136660, "male_as": 56, "male_b": 24, "male_bk": 9539, "male_in": 9, "male_lb": 38, "male_lt": 1254, "male_lw": 829, "male_w": 18, "male_wh": 1158, "resource_uri": "/api/1.0/dailypopulationcounts/136660/", "total": 14182}, {"booking_date": "2013-09-20", "female_as": 7, "female_b": 2, "female_bk": 910, "female_in": 0, "female_lb": 7, "female_lt": 35, "female_lw": 80, "female_w": 1, "female_wh": 213, "id": 136518, "male_as": 56, "male_b": 24, "male_bk": 9479, "male_in": 8, "male_lb": 41, "male_lt": 1238, "male_lw": 824, "male_w": 17, "male_wh": 1144, "resource_uri": "/api/1.0/dailypopulationcounts/136518/", "total": 14087}, {"booking_date": "2013-09-21", "female_as": 7, "female_b": 2, "female_bk": 910, "female_in": 0, "female_lb": 7, "female_lt": 35, "female_lw": 81, "female_w": 1, "female_wh": 211, "id": 136589, "male_as": 55, "male_b": 23, "male_bk": 9428, "male_in": 9, "male_lb": 39, "male_lt": 1224, "male_lw": 827, "male_w": 17, "male_wh": 1143, "resource_uri": "/api/1.0/dailypopulationcounts/136589/", "total": 14020}, {"booking_date": "2013-09-22", "female_as": 7, "female_b": 2, "female_bk": 922, "female_in": 0, "female_lb": 7, "female_lt": 34, "female_lw": 80, "female_w": 1, "female_wh": 212, "id": 136711, "male_as": 55, "male_b": 23, "male_bk": 9492, "male_in": 9, "male_lb": 39, "male_lt": 1234, "male_lw": 825, "male_w": 17, "male_wh": 1146, "resource_uri": "/api/1.0/dailypopulationcounts/136711/", "total": 14106}, {"booking_date": "2013-09-23", "female_as": 7, "female_b": 2, "female_bk": 941, "female_in": 0, "female_lb": 7, "female_lt": 35, "female_lw": 82, "female_w": 1, "female_wh": 214, "id": 136587, "male_as": 56, "male_b": 23, "male_bk": 9580, "male_in": 9, "male_lb": 39, "male_lt": 1249, "male_lw": 837, "male_w": 17, "male_wh": 1159, "resource_uri": "/api/1.0/dailypopulationcounts/136587/", "total": 14259}, {"booking_date": "2013-09-24", "female_as": 8, "female_b": 2, "female_bk": 940, "female_in": 0, "female_lb": 7, "female_lt": 36, "female_lw": 81, "female_w": 1, "female_wh": 211, "id": 136728, "male_as": 56, "male_b": 22, "male_bk": 9510, "male_in": 9, "male_lb": 39, "male_lt": 1238, "male_lw": 830, "male_w": 18, "male_wh": 1158, "resource_uri": "/api/1.0/dailypopulationcounts/136728/", "total": 14168}, {"booking_date": "2013-09-25", "female_as": 8, "female_b": 2, "female_bk": 938, "female_in": 0, "female_lb": 7, "female_lt": 34, "female_lw": 79, "female_w": 1, "female_wh": 207, "id": 136593, "male_as": 55, "male_b": 21, "male_bk": 9434, "male_in": 9, "male_lb": 39, "male_lt": 1226, "male_lw": 820, "male_w": 18, "male_wh": 1155, "resource_uri": "/api/1.0/dailypopulationcounts/136593/", "total": 14055}, {"booking_date": "2013-09-26", "female_as": 8, "female_b": 1, "female_bk": 919, "female_in": 0, "female_lb": 8, "female_lt": 32, "female_lw": 75, "female_w": 1, "female_wh": 214, "id": 136592, "male_as": 55, "male_b": 21, "male_bk": 9462, "male_in": 10, "male_lb": 39, "male_lt": 1231, "male_lw": 820, "male_w": 18, "male_wh": 1151, "resource_uri": "/api/1.0/dailypopulationcounts/136592/", "total": 14067}, {"booking_date": "2013-09-27", "female_as": 8, "female_b": 1, "female_bk": 927, "female_in": 0, "female_lb": 8, "female_lt": 32, "female_lw": 76, "female_w": 1, "female_wh": 215, "id": 136591, "male_as": 57, "male_b": 21, "male_bk": 9419, "male_in": 10, "male_lb": 39, "male_lt": 1228, "male_lw": 821, "male_w": 17, "male_wh": 1142, "resource_uri": "/api/1.0/dailypopulationcounts/136591/", "total": 14024}, {"booking_date": "2013-09-28", "female_as": 8, "female_b": 1, "female_bk": 916, "female_in": 0, "female_lb": 8, "female_lt": 34, "female_lw": 79, "female_w": 1, "female_wh": 213, "id": 136596, "male_as": 55, "male_b": 22, "male_bk": 9327, "male_in": 10, "male_lb": 36, "male_lt": 1212, "male_lw": 806, "male_w": 17, "male_wh": 1131, "resource_uri": "/api/1.0/dailypopulationcounts/136596/", "total": 13878}, {"booking_date": "2013-09-29", "female_as": 8, "female_b": 1, "female_bk": 912, "female_in": 0, "female_lb": 8, "female_lt": 35, "female_lw": 76, "female_w": 1, "female_wh": 212, "id": 136595, "male_as": 53, "male_b": 22, "male_bk": 9325, "male_in": 10, "male_lb": 35, "male_lt": 1202, "male_lw": 801, "male_w": 16, "male_wh": 1127, "resource_uri": "/api/1.0/dailypopulationcounts/136595/", "total": 13846}, {"booking_date": "2013-09-30", "female_as": 8, "female_b": 1, "female_bk": 931, "female_in": 0, "female_lb": 8, "female_lt": 35, "female_lw": 76, "female_w": 1, "female_wh": 217, "id": 136521, "male_as": 53, "male_b": 22, "male_bk": 9420, "male_in": 10, "male_lb": 35, "male_lt": 1226, "male_lw": 811, "male_w": 17, "male_wh": 1149, "resource_uri": "/api/1.0/dailypopulationcounts/136521/", "total": 14022}, {"booking_date": "2013-10-01", "female_as": 8, "female_b": 1, "female_bk": 940, "female_in": 0, "female_lb": 8, "female_lt": 34, "female_lw": 78, "female_w": 1, "female_wh": 220, "id": 136520, "male_as": 52, "male_b": 23, "male_bk": 9453, "male_in": 10, "male_lb": 35, "male_lt": 1232, "male_lw": 810, "male_w": 17, "male_wh": 1151, "resource_uri": "/api/1.0/dailypopulationcounts/136520/", "total": 14075}, {"booking_date": "2013-10-02", "female_as": 7, "female_b": 1, "female_bk": 935, "female_in": 0, "female_lb": 8, "female_lt": 34, "female_lw": 76, "female_w": 1, "female_wh": 216, "id": 136519, "male_as": 50, "male_b": 22, "male_bk": 9425, "male_in": 9, "male_lb": 35, "male_lt": 1216, "male_lw": 809, "male_w": 17, "male_wh": 1142, "resource_uri": "/api/1.0/dailypopulationcounts/136519/", "total": 14005}, {"booking_date": "2013-10-03", "female_as": 7, "female_b": 1, "female_bk": 922, "female_in": 0, "female_lb": 9, "female_lt": 34, "female_lw": 74, "female_w": 1, "female_wh": 216, "id": 136715, "male_as": 50, "male_b": 21, "male_bk": 9448, "male_in": 9, "male_lb": 36, "male_lt": 1211, "male_lw": 810, "male_w": 18, "male_wh": 1154, "resource_uri": "/api/1.0/dailypopulationcounts/136715/", "total": 14022}, {"booking_date": "2013-10-04", "female_as": 7, "female_b": 1, "female_bk": 922, "female_in": 0, "female_lb": 9, "female_lt": 32, "female_lw": 75, "female_w": 1, "female_wh": 213, "id": 136517, "male_as": 49, "male_b": 20, "male_bk": 9410, "male_in": 8, "male_lb": 36, "male_lt": 1213, "male_lw": 804, "male_w": 18, "male_wh": 1151, "resource_uri": "/api/1.0/dailypopulationcounts/136517/", "total": 13970}, {"booking_date": "2013-10-05", "female_as": 7, "female_b": 1, "female_bk": 903, "female_in": 0, "female_lb": 10, "female_lt": 32, "female_lw": 77, "female_w": 1, "female_wh": 206, "id": 136634, "male_as": 49, "male_b": 20, "male_bk": 9334, "male_in": 8, "male_lb": 36, "male_lt": 1209, "male_lw": 800, "male_w": 17, "male_wh": 1124, "resource_uri": "/api/1.0/dailypopulationcounts/136634/", "total": 13835}, {"booking_date": "2013-10-06", "female_as": 7, "female_b": 1, "female_bk": 914, "female_in": 0, "female_lb": 10, "female_lt": 32, "female_lw": 79, "female_w": 1, "female_wh": 206, "id": 136515, "male_as": 49, "male_b": 20, "male_bk": 9431, "male_in": 9, "male_lb": 37, "male_lt": 1223, "male_lw": 811, "male_w": 17, "male_wh": 1132, "resource_uri": "/api/1.0/dailypopulationcounts/136515/", "total": 13980}, {"booking_date": "2013-10-07", "female_as": 7, "female_b": 1, "female_bk": 926, "female_in": 0, "female_lb": 10, "female_lt": 32, "female_lw": 81, "female_w": 1, "female_wh": 212, "id": 136514, "male_as": 51, "male_b": 22, "male_bk": 9484, "male_in": 10, "male_lb": 37, "male_lt": 1241, "male_lw": 824, "male_w": 17, "male_wh": 1146, "resource_uri": "/api/1.0/dailypopulationcounts/136514/", "total": 14103}, {"booking_date": "2013-10-08", "female_as": 7, "female_b": 1, "female_bk": 928, "female_in": 0, "female_lb": 9, "female_lt": 33, "female_lw": 81, "female_w": 1, "female_wh": 211, "id": 136499, "male_as": 51, "male_b": 22, "male_bk": 9447, "male_in": 10, "male_lb": 38, "male_lt": 1243, "male_lw": 819, "male_w": 17, "male_wh": 1139, "resource_uri": "/api/1.0/dailypopulationcounts/136499/", "total": 14058}, {"booking_date": "2013-10-09", "female_as": 8, "female_b": 1, "female_bk": 924, "female_in": 1, "female_lb": 8, "female_lt": 34, "female_lw": 82, "female_w": 1, "female_wh": 211, "id": 136629, "male_as": 51, "male_b": 22, "male_bk": 9417, "male_in": 10, "male_lb": 37, "male_lt": 1235, "male_lw": 810, "male_w": 16, "male_wh": 1136, "resource_uri": "/api/1.0/dailypopulationcounts/136629/", "total": 14005}, {"booking_date": "2013-10-10", "female_as": 9, "female_b": 1, "female_bk": 910, "female_in": 1, "female_lb": 8, "female_lt": 36, "female_lw": 81, "female_w": 1, "female_wh": 202, "id": 136781, "male_as": 52, "male_b": 22, "male_bk": 9397, "male_in": 9, "male_lb": 35, "male_lt": 1234, "male_lw": 811, "male_w": 15, "male_wh": 1134, "resource_uri": "/api/1.0/dailypopulationcounts/136781/", "total": 13959}, {"booking_date": "2013-10-11", "female_as": 8, "female_b": 1, "female_bk": 917, "female_in": 1, "female_lb": 8, "female_lt": 38, "female_lw": 80, "female_w": 1, "female_wh": 199, "id": 136719, "male_as": 49, "male_b": 22, "male_bk": 9385, "male_in": 9, "male_lb": 33, "male_lt": 1227, "male_lw": 808, "male_w": 14, "male_wh": 1129, "resource_uri": "/api/1.0/dailypopulationcounts/136719/", "total": 13930}, {"booking_date": "2013-10-12", "female_as": 8, "female_b": 1, "female_bk": 922, "female_in": 1, "female_lb": 8, "female_lt": 35, "female_lw": 78, "female_w": 1, "female_wh": 194, "id": 136739, "male_as": 48, "male_b": 23, "male_bk": 9347, "male_in": 9, "male_lb": 30, "male_lt": 1217, "male_lw": 807, "male_w": 15, "male_wh": 1119, "resource_uri": "/api/1.0/dailypopulationcounts/136739/", "total": 13864}, {"booking_date": "2013-10-13", "female_as": 8, "female_b": 1, "female_bk": 933, "female_in": 1, "female_lb": 8, "female_lt": 35, "female_lw": 79, "female_w": 1, "female_wh": 199, "id": 136784, "male_as": 49, "male_b": 23, "male_bk": 9404, "male_in": 10, "male_lb": 31, "male_lt": 1219, "male_lw": 813, "male_w": 15, "male_wh": 1129, "resource_uri": "/api/1.0/dailypopulationcounts/136784/", "total": 13959}, {"booking_date": "2013-10-14", "female_as": 8, "female_b": 1, "female_bk": 946, "female_in": 1, "female_lb": 8, "female_lt": 35, "female_lw": 79, "female_w": 1, "female_wh": 201, "id": 136785, "male_as": 49, "male_b": 23, "male_bk": 9456, "male_in": 10, "male_lb": 32, "male_lt": 1224, "male_lw": 808, "male_w": 15, "male_wh": 1141, "resource_uri": "/api/1.0/dailypopulationcounts/136785/", "total": 14039}, {"booking_date": "2013-10-15", "female_as": 8, "female_b": 1, "female_bk": 958, "female_in": 1, "female_lb": 8, "female_lt": 35, "female_lw": 84, "female_w": 2, "female_wh": 206, "id": 136709, "male_as": 51, "male_b": 23, "male_bk": 9549, "male_in": 10, "male_lb": 33, "male_lt": 1233, "male_lw": 818, "male_w": 15, "male_wh": 1154, "resource_uri": "/api/1.0/dailypopulationcounts/136709/", "total": 14190}, {"booking_date": "2013-10-16", "female_as": 8, "female_b": 1, "female_bk": 947, "female_in": 1, "female_lb": 8, "female_lt": 35, "female_lw": 83, "female_w": 2, "female_wh": 209, "id": 136710, "male_as": 53, "male_b": 22, "male_bk": 9488, "male_in": 10, "male_lb": 33, "male_lt": 1216, "male_lw": 813, "male_w": 15, "male_wh": 1139, "resource_uri": "/api/1.0/dailypopulationcounts/136710/", "total": 14084}, {"booking_date": "2013-10-17", "female_as": 8, "female_b": 1, "female_bk": 918, "female_in": 1, "female_lb": 8, "female_lt": 35, "female_lw": 81, "female_w": 2, "female_wh": 205, "id": 136713, "male_as": 51, "male_b": 23, "male_bk": 9495, "male_in": 10, "male_lb": 31, "male_lt": 1209, "male_lw": 821, "male_w": 15, "male_wh": 1119, "resource_uri": "/api/1.0/dailypopulationcounts/136713/", "total": 14034}, {"booking_date": "2013-10-18", "female_as": 9, "female_b": 1, "female_bk": 903, "female_in": 1, "female_lb": 8, "female_lt": 35, "female_lw": 79, "female_w": 1, "female_wh": 200, "id": 136716, "male_as": 52, "male_b": 23, "male_bk": 9448, "male_in": 9, "male_lb": 33, "male_lt": 1196, "male_lw": 819, "male_w": 14, "male_wh": 1106, "resource_uri": "/api/1.0/dailypopulationcounts/136716/", "total": 13938}, {"booking_date": "2013-10-19", "female_as": 9, "female_b": 1, "female_bk": 903, "female_in": 1, "female_lb": 8, "female_lt": 33, "female_lw": 76, "female_w": 1, "female_wh": 197, "id": 136718, "male_as": 51, "male_b": 24, "male_bk": 9359, "male_in": 9, "male_lb": 31, "male_lt": 1186, "male_lw": 823, "male_w": 14, "male_wh": 1096, "resource_uri": "/api/1.0/dailypopulationcounts/136718/", "total": 13823}, {"booking_date": "2013-10-20", "female_as": 9, "female_b": 1, "female_bk": 914, "female_in": 1, "female_lb": 8, "female_lt": 33, "female_lw": 79, "female_w": 1, "female_wh": 201, "id": 136502, "male_as": 51, "male_b": 25, "male_bk": 9426, "male_in": 9, "male_lb": 32, "male_lt": 1193, "male_lw": 825, "male_w": 14, "male_wh": 1103, "resource_uri": "/api/1.0/dailypopulationcounts/136502/", "total": 13926}, {"booking_date": "2013-10-21", "female_as": 10, "female_b": 2, "female_bk": 924, "female_in": 1, "female_lb": 8, "female_lt": 35, "female_lw": 81, "female_w": 1, "female_wh": 207, "id": 136747, "male_as": 50, "male_b": 27, "male_bk": 9511, "male_in": 9, "male_lb": 32, "male_lt": 1210, "male_lw": 841, "male_w": 19, "male_wh": 1114, "resource_uri": "/api/1.0/dailypopulationcounts/136747/", "total": 14083}, {"booking_date": "2013-10-22", "female_as": 11, "female_b": 2, "female_bk": 914, "female_in": 1, "female_lb": 8, "female_lt": 33, "female_lw": 81, "female_w": 1, "female_wh": 205, "id": 136750, "male_as": 51, "male_b": 27, "male_bk": 9511, "male_in": 9, "male_lb": 30, "male_lt": 1201, "male_lw": 845, "male_w": 19, "male_wh": 1107, "resource_uri": "/api/1.0/dailypopulationcounts/136750/", "total": 14057}, {"booking_date": "2013-10-23", "female_as": 10, "female_b": 2, "female_bk": 897, "female_in": 1, "female_lb": 8, "female_lt": 32, "female_lw": 83, "female_w": 1, "female_wh": 201, "id": 136749, "male_as": 52, "male_b": 28, "male_bk": 9500, "male_in": 9, "male_lb": 30, "male_lt": 1192, "male_lw": 844, "male_w": 15, "male_wh": 1095, "resource_uri": "/api/1.0/dailypopulationcounts/136749/", "total": 14001}, {"booking_date": "2013-10-24", "female_as": 10, "female_b": 2, "female_bk": 873, "female_in": 1, "female_lb": 8, "female_lt": 33, "female_lw": 81, "female_w": 1, "female_wh": 202, "id": 136744, "male_as": 54, "male_b": 29, "male_bk": 9485, "male_in": 9, "male_lb": 30, "male_lt": 1193, "male_lw": 843, "male_w": 15, "male_wh": 1091, "resource_uri": "/api/1.0/dailypopulationcounts/136744/", "total": 13961}, {"booking_date": "2013-10-25", "female_as": 10, "female_b": 1, "female_bk": 878, "female_in": 1, "female_lb": 7, "female_lt": 33, "female_lw": 82, "female_w": 1, "female_wh": 201, "id": 136743, "male_as": 54, "male_b": 29, "male_bk": 9422, "male_in": 9, "male_lb": 28, "male_lt": 1187, "male_lw": 836, "male_w": 15, "male_wh": 1084, "resource_uri": "/api/1.0/dailypopulationcounts/136743/", "total": 13879}, {"booking_date": "2013-10-26", "female_as": 11, "female_b": 1, "female_bk": 871, "female_in": 1, "female_lb": 7, "female_lt": 33, "female_lw": 79, "female_w": 1, "female_wh": 201, "id": 136746, "male_as": 51, "male_b": 29, "male_bk": 9309, "male_in": 9, "male_lb": 28, "male_lt": 1169, "male_lw": 826, "male_w": 15, "male_wh": 1068, "resource_uri": "/api/1.0/dailypopulationcounts/136746/", "total": 13710}, {"booking_date": "2013-10-27", "female_as": 11, "female_b": 1, "female_bk": 873, "female_in": 1, "female_lb": 7, "female_lt": 33, "female_lw": 81, "female_w": 1, "female_wh": 206, "id": 136745, "male_as": 50, "male_b": 29, "male_bk": 9354, "male_in": 9, "male_lb": 30, "male_lt": 1180, "male_lw": 828, "male_w": 16, "male_wh": 1075, "resource_uri": "/api/1.0/dailypopulationcounts/136745/", "total": 13786}, {"booking_date": "2013-10-28", "female_as": 11, "female_b": 1, "female_bk": 883, "female_in": 1, "female_lb": 7, "female_lt": 33, "female_lw": 83, "female_w": 1, "female_wh": 209, "id": 136742, "male_as": 51, "male_b": 29, "male_bk": 9439, "male_in": 9, "male_lb": 30, "male_lt": 1185, "male_lw": 838, "male_w": 16, "male_wh": 1090, "resource_uri": "/api/1.0/dailypopulationcounts/136742/", "total": 13917}, {"booking_date": "2013-10-29", "female_as": 10, "female_b": 1, "female_bk": 866, "female_in": 1, "female_lb": 7, "female_lt": 34, "female_lw": 80, "female_w": 1, "female_wh": 205, "id": 136741, "male_as": 51, "male_b": 29, "male_bk": 9266, "male_in": 9, "male_lb": 30, "male_lt": 1171, "male_lw": 830, "male_w": 14, "male_wh": 1064, "resource_uri": "/api/1.0/dailypopulationcounts/136741/", "total": 13670}, {"booking_date": "2013-10-30", "female_as": 10, "female_b": 1, "female_bk": 894, "female_in": 1, "female_lb": 7, "female_lt": 35, "female_lw": 81, "female_w": 1, "female_wh": 210, "id": 136714, "male_as": 51, "male_b": 29, "male_bk": 9404, "male_in": 9, "male_lb": 30, "male_lt": 1190, "male_lw": 843, "male_w": 14, "male_wh": 1086, "resource_uri": "/api/1.0/dailypopulationcounts/136714/", "total": 13897}, {"booking_date": "2013-10-31", "female_as": 10, "female_b": 1, "female_bk": 867, "female_in": 1, "female_lb": 7, "female_lt": 35, "female_lw": 79, "female_w": 1, "female_wh": 202, "id": 136496, "male_as": 53, "male_b": 28, "male_bk": 9279, "male_in": 10, "male_lb": 29, "male_lt": 1171, "male_lw": 836, "male_w": 14, "male_wh": 1068, "resource_uri": "/api/1.0/dailypopulationcounts/136496/", "total": 13692}, {"booking_date": "2013-11-01", "female_as": 10, "female_b": 1, "female_bk": 870, "female_in": 1, "female_lb": 7, "female_lt": 33, "female_lw": 80, "female_w": 1, "female_wh": 204, "id": 136665, "male_as": 54, "male_b": 28, "male_bk": 9294, "male_in": 10, "male_lb": 29, "male_lt": 1174, "male_lw": 849, "male_w": 14, "male_wh": 1073, "resource_uri": "/api/1.0/dailypopulationcounts/136665/", "total": 13733}, {"booking_date": "2013-11-02", "female_as": 11, "female_b": 1, "female_bk": 869, "female_in": 1, "female_lb": 7, "female_lt": 34, "female_lw": 77, "female_w": 1, "female_wh": 199, "id": 136759, "male_as": 52, "male_b": 26, "male_bk": 9172, "male_in": 10, "male_lb": 29, "male_lt": 1154, "male_lw": 835, "male_w": 13, "male_wh": 1049, "resource_uri": "/api/1.0/dailypopulationcounts/136759/", "total": 13541}, {"booking_date": "2013-11-03", "female_as": 11, "female_b": 1, "female_bk": 889, "female_in": 2, "female_lb": 7, "female_lt": 34, "female_lw": 79, "female_w": 1, "female_wh": 203, "id": 136760, "male_as": 53, "male_b": 27, "male_bk": 9260, "male_in": 10, "male_lb": 29, "male_lt": 1168, "male_lw": 848, "male_w": 13, "male_wh": 1067, "resource_uri": "/api/1.0/dailypopulationcounts/136760/", "total": 13703}, {"booking_date": "2013-11-04", "female_as": 11, "female_b": 1, "female_bk": 908, "female_in": 2, "female_lb": 7, "female_lt": 36, "female_lw": 84, "female_w": 1, "female_wh": 208, "id": 136754, "male_as": 54, "male_b": 27, "male_bk": 9331, "male_in": 10, "male_lb": 27, "male_lt": 1186, "male_lw": 853, "male_w": 13, "male_wh": 1087, "resource_uri": "/api/1.0/dailypopulationcounts/136754/", "total": 13847}, {"booking_date": "2013-11-05", "female_as": 12, "female_b": 1, "female_bk": 909, "female_in": 2, "female_lb": 8, "female_lt": 37, "female_lw": 83, "female_w": 1, "female_wh": 210, "id": 136755, "male_as": 54, "male_b": 27, "male_bk": 9304, "male_in": 10, "male_lb": 27, "male_lt": 1176, "male_lw": 838, "male_w": 14, "male_wh": 1079, "resource_uri": "/api/1.0/dailypopulationcounts/136755/", "total": 13793}, {"booking_date": "2013-11-06", "female_as": 12, "female_b": 1, "female_bk": 905, "female_in": 1, "female_lb": 7, "female_lt": 39, "female_lw": 80, "female_w": 1, "female_wh": 203, "id": 136756, "male_as": 53, "male_b": 27, "male_bk": 9277, "male_in": 9, "male_lb": 27, "male_lt": 1170, "male_lw": 832, "male_w": 14, "male_wh": 1074, "resource_uri": "/api/1.0/dailypopulationcounts/136756/", "total": 13733}, {"booking_date": "2013-11-07", "female_as": 10, "female_b": 1, "female_bk": 887, "female_in": 1, "female_lb": 7, "female_lt": 37, "female_lw": 76, "female_w": 1, "female_wh": 198, "id": 136757, "male_as": 54, "male_b": 26, "male_bk": 9296, "male_in": 9, "male_lb": 27, "male_lt": 1172, "male_lw": 832, "male_w": 14, "male_wh": 1079, "resource_uri": "/api/1.0/dailypopulationcounts/136757/", "total": 13728}, {"booking_date": "2013-11-08", "female_as": 10, "female_b": 1, "female_bk": 877, "female_in": 1, "female_lb": 7, "female_lt": 37, "female_lw": 76, "female_w": 1, "female_wh": 204, "id": 136752, "male_as": 55, "male_b": 26, "male_bk": 9227, "male_in": 9, "male_lb": 26, "male_lt": 1170, "male_lw": 827, "male_w": 14, "male_wh": 1073, "resource_uri": "/api/1.0/dailypopulationcounts/136752/", "total": 13642}, {"booking_date": "2013-11-09", "female_as": 10, "female_b": 1, "female_bk": 903, "female_in": 1, "female_lb": 7, "female_lt": 38, "female_lw": 77, "female_w": 1, "female_wh": 206, "id": 136753, "male_as": 55, "male_b": 26, "male_bk": 9321, "male_in": 9, "male_lb": 26, "male_lt": 1174, "male_lw": 838, "male_w": 14, "male_wh": 1085, "resource_uri": "/api/1.0/dailypopulationcounts/136753/", "total": 13793}, {"booking_date": "2013-11-10", "female_as": 10, "female_b": 1, "female_bk": 918, "female_in": 1, "female_lb": 7, "female_lt": 38, "female_lw": 77, "female_w": 1, "female_wh": 210, "id": 136751, "male_as": 55, "male_b": 26, "male_bk": 9405, "male_in": 9, "male_lb": 28, "male_lt": 1194, "male_lw": 852, "male_w": 14, "male_wh": 1107, "resource_uri": "/api/1.0/dailypopulationcounts/136751/", "total": 13954}, {"booking_date": "2013-11-11", "female_as": 10, "female_b": 1, "female_bk": 916, "female_in": 1, "female_lb": 7, "female_lt": 37, "female_lw": 76, "female_w": 1, "female_wh": 205, "id": 136540, "male_as": 54, "male_b": 26, "male_bk": 9354, "male_in": 9, "male_lb": 29, "male_lt": 1188, "male_lw": 838, "male_w": 14, "male_wh": 1094, "resource_uri": "/api/1.0/dailypopulationcounts/136540/", "total": 13861}]}